medmnistc/__init__.py
medmnistc/augmentation.py
medmnistc/dataset.py
medmnistc/dataset_manager.py
medmnistc/eval.py
medmnistc/visualizer.py
medmnistc/assets/inks.npz
medmnistc/corruptions/__init__.py
medmnistc/corruptions/base.py
medmnistc/corruptions/compression.py
medmnistc/corruptions/enhance.py
medmnistc/corruptions/filter.py
medmnistc/corruptions/microscopy.py
medmnistc/corruptions/noise.py
medmnistc/corruptions/registry.py
medmnistc/utils/baselines.py
medmnistc/utils/utils.py
medmnistc-0.1.0.dist-info/METADATA
medmnistc-0.1.0.dist-info/WHEEL
medmnistc-0.1.0.dist-info/licenses/LICENSE
medmnistc-0.1.0.dist-info/RECORD
