Metadata-Version: 2.3
Name: medmnistc
Version: 0.1.0
Summary: This Python library aims to evaluate model robustness under corrupted test sets and to enhance domain generalization through domain-specific augmentations.
Project-URL: Homepage, https://github.com/francescodisalvo05/medmnistc-api
Project-URL: Issue Tracker, https://github.com/francescodisalvo05/medmnistc-api/issues
Author-email: Francesco Di Salvo <francesco.di-salvo@uni-bamberg.de>
License-File: LICENSE
Requires-Python: >=3.7
Requires-Dist: medmnist==3.0.1
Requires-Dist: numpy
Requires-Dist: opencv-python
Requires-Dist: scikit-image==0.23.2
Requires-Dist: scikit-learn>1.2.2
Requires-Dist: scipy
Requires-Dist: torch
Requires-Dist: torchvision
Requires-Dist: wand>0.6.10
